{"id": "search=Dwight+Girls+Navy+Blazer", "name": "Dwight Girls Navy Blazer", "category": "Search", "thumbnails": ["https://www.braggsschoolwear.co.uk/image/cache/catalog/Dwight/girls%20dwight%20blazer-500x500.jpg"], "product_name": "Dwight Girls Navy Blazer", "product_description_paragraphs": [], "product_price": "29.95", "variant_choice": {"parameter": "Chest Size", "options": ["32(+\u00a35.00)", "34(+\u00a35.00)", "36(+\u00a310.00)"]}, "brand": "BRAGGS", "product_code": "DW022", "availability": "Out Of Stock"}