{"id": "167", "name": "Sacred Heart White Polo Shirt / Green Trim (with Logo)", "category": "Specialist Schoolwear", "thumbnails": ["https://www.braggsschoolwear.co.uk/image/cache/catalog/13-500x500.jpg"], "product_name": "Sacred Heart White Polo Shirt / Green Trim (with Logo)", "product_description_paragraphs": ["Rception Boys and Girls", "Summer Term for Rest of School"], "product_price": "11.95", "variant_choice": {"parameter": "Size", "options": ["Age4/5(+\u00a31.00)", "Age5/6(+\u00a31.00)", "Age7/8(+\u00a31.00)", "Age9/10(+\u00a31.00)", "Age11/12(+\u00a31.00)", "Age13(+\u00a32.00)", "SmallAdult(+\u00a32.00)", "Medium(+\u00a32.00)"]}, "brand": "David Luke", "product_code": "SH015", "availability": "In Stock"}