{"id": "211", "name": "St. Theresa's Back Pack (with Logo)", "category": ",Accessories,Back Pack", "thumbnails": ["https://www.braggsschoolwear.co.uk/image/cache/catalog/Tudor/St%20Theresa%20backpack-500x500.jpg"], "product_name": "St. Theresa's Back Pack (with Logo)", "product_description_paragraphs": ["Ideal for Students from Year 3 to Year 6"], "product_price": "16.95", "variant_choice": {"parameter": "Size", "options": ["OneSizeFitsAll"]}, "brand": "William Turner", "product_code": "ST012", "availability": "In Stock"}