{"id": "190", "name": "St. Theresa's Boys V-Neck Jumper (with Logo)", "category": ",Specialist Schoolwear,Primary Schools,St Theresa's School", "thumbnails": ["https://www.braggsschoolwear.co.uk/image/cache/catalog/162-500x500.jpg"], "product_name": "St. Theresa's Boys V-Neck Jumper (with Logo)", "product_description_paragraphs": [], "product_price": "17.95", "variant_choice": {"parameter": "Chest Size", "options": ["26", "28(+\u00a32.00)", "30(+\u00a32.00)", "32(+\u00a34.00)", "34(+\u00a34.00)"]}, "brand": "BRAGGS", "product_code": "ST001", "availability": "In Stock"}